.coveragerc
.dockerignore
.gitignore
.pre-commit-config.yaml
LICENSE
MANIFEST.in
README.md
pyproject.toml
requirements.txt
requirements_dev.txt
requirements_doc.txt
setup.cfg
setup.py
.github/workflows/github-actions.yml
deker_shell/__init__.py
deker_shell/completer.py
deker_shell/config.py
deker_shell/consts.py
deker_shell/help.py
deker_shell/main.py
deker_shell/utils.py
deker_shell.egg-info/PKG-INFO
deker_shell.egg-info/SOURCES.txt
deker_shell.egg-info/dependency_links.txt
deker_shell.egg-info/entry_points.txt
deker_shell.egg-info/requires.txt
deker_shell.egg-info/top_level.txt
docs/Makefile
docs/conf.py
docs/index.rst
docs/make.bat
tests/__init__.py
tests/test_start.py